{
  "parent": "minecraft:recipes/root",
  "rewards": {
    "recipes": [
      "cores:chromium_dust_smelting"
    ]
  },
  "criteria": {
    "chromium_dust": {
      "trigger": "minecraft:inventory_changed",
      "conditions": {
        "items": [
          {
            "item": "cores:chromium_dust"
          }
        ]
      }
    },
    "has_the_recipe": {
      "trigger": "minecraft:recipe_unlocked",
      "conditions": {
        "recipe": "cores:chromium_dust_smelting"
      }
    }
  },
  "requirements": [
    [
      "chromium_dust",
      "has_the_recipe"
    ]
  ]
}