{
  "parent": "minecraft:recipes/root",
  "rewards": {
    "recipes": [
      "cores:invar_ingot_smelting"
    ]
  },
  "criteria": {
    "invar_blend": {
      "trigger": "minecraft:inventory_changed",
      "conditions": {
        "items": [
          {
            "item": "cores:invar_blend"
          }
        ]
      }
    },
    "has_the_recipe": {
      "trigger": "minecraft:recipe_unlocked",
      "conditions": {
        "recipe": "cores:invar_ingot_smelting"
      }
    }
  },
  "requirements": [
    [
      "invar_blend",
      "has_the_recipe"
    ]
  ]
}